stg_net/__about__.py
stg_net/__init__.py
stg_net/conn.py
stg_net/helper.py
stg_net/input.py
stg_net/neuron.py
stg_net-0.0.1.dist-info/METADATA
stg_net-0.0.1.dist-info/WHEEL
stg_net-0.0.1.dist-info/licenses/LICENSE.txt
stg_net-0.0.1.dist-info/RECORD
